pytest_ot/__init__.py
pytest_ot/instrumentation.py
pytest_ot/plugin.py
pytest_ot/resource.py
pytest_ot-0.0.7.dist-info/LICENSE
pytest_ot-0.0.7.dist-info/METADATA
pytest_ot-0.0.7.dist-info/WHEEL
pytest_ot-0.0.7.dist-info/entry_points.txt
pytest_ot-0.0.7.dist-info/top_level.txt
pytest_ot-0.0.7.dist-info/RECORD
