Metadata-Version: 2.1
Name: pytest-ot
Version: 0.0.7
Summary: A pytest plugin for instrumenting test runs via OpenTelemetry
Author-email: Chris Guidry <chris@theguidrys.us>, Drobyshev Maksim <sibmaks@vk.com>
Project-URL: Homepage, https://github.com/sibmaks/pytest-ot
Project-URL: Issues, https://github.com/sibmaks/pytest-ot/issues
Classifier: Programming Language :: Python :: 3
Classifier: License :: OSI Approved :: MIT License
Classifier: Operating System :: OS Independent
Classifier: Framework :: Pytest
Requires-Python: >=3.8
License-File: LICENSE
Provides-Extra: dev
Requires-Dist: black ; extra == 'dev'
Requires-Dist: build ; extra == 'dev'
Requires-Dist: flake8 ; extra == 'dev'
Requires-Dist: flake8-black ; extra == 'dev'
Requires-Dist: isort ; extra == 'dev'
Requires-Dist: mypy ; extra == 'dev'
Requires-Dist: pre-commit ; extra == 'dev'
Requires-Dist: pytest ; extra == 'dev'
Requires-Dist: pytest-cov ; extra == 'dev'
Requires-Dist: pytest-xdist ; extra == 'dev'
Requires-Dist: twine ; extra == 'dev'
